Asynch_Fifo.v
module Asynch_Fifo (
    input wr_clk, rd_clk, rst,           // Separate write and read clocks, and a reset signal
    input wr_en, rd_en,                 // Write and read enable signals
    input [7:0] buf_in,                // Input data to write to FIFO
    output reg [7:0] buf_out,         // Output data read from FIFO
    output reg buf_empty, buf_full   // Flags to indicate empty and full status of FIFO
);

  ///////////////////////////////////
 /////////     Parameters   ////////                 
///////////////////////////////////
parameter DEPTH = 64;                   // Depth of the FIFO (number of entries)
parameter ADDR_WIDTH = 6;              // Width of the address pointers (Log2(DEPTH))

  /////////////////////////////////////
 ///////// Memory for FIFO ///////////
/////////////////////////////////////
reg [7:0] buf_mem [0:DEPTH-1];     // Dual-port memory to store FIFO data

  ///////////////////////////////////////////////
 ///// Write and Read Pointers (Gray-coded) ////
///////////////////////////////////////////////
reg [ADDR_WIDTH:0] head, tail;                            // Binary write and read pointers
reg [ADDR_WIDTH:0] head_gray, tail_gray;                 // Gray-coded pointers for synchronization

// Synchronizer Registers
reg [ADDR_WIDTH:0] head_gray_sync1, head_gray_sync2;   // Synchronized write pointer in read domain
reg [ADDR_WIDTH:0] tail_gray_sync1, tail_gray_sync2;  // Synchronized read pointer in write domain

  /////////////////////////////////////
 //////// Empty and Full Flags ///////          
/////////////////////////////////////
// Flags derived from synchronized pointers
wire empty_flag;
wire full_flag;

assign empty_flag = (head_gray_sync2 == tail_gray);                                                 
assign full_flag  = (head_gray == {~tail_gray_sync2[ADDR_WIDTH], tail_gray_sync2[ADDR_WIDTH-1:0]}); 

  ///////////////////////////////////////////////////
 ///// Write Pointer Update Logic with Gray Code ///
///////////////////////////////////////////////////
always @(posedge wr_clk or posedge rst) begin
    if (rst) begin
        head <= 0;                        // Reset write pointer to 0
        head_gray <= 0;                   // Reset Gray-coded write pointer
    end 
    else if (wr_en && !buf_full) begin    // Write only if enabled and not full
        buf_mem[head[ADDR_WIDTH-1:0]] <= buf_in;  // Write data into memory
        head <= head + 1;                          // Increment binary write pointer
        head_gray <= (head + 1) ^ ((head + 1) >> 1); // Convert binary to Gray code
    end
end

  ////////////////////////////////////////////////////
 ///// Read Pointer Update Logic with Gray Code ////
////////////////////////////////////////////////////
always @(posedge rd_clk or posedge rst) begin
    if (rst) begin
        tail <= 0;                       // Reset read pointer to 0
        tail_gray <= 0;                  // Reset Gray-coded read pointer
    end 
    else if (rd_en && !buf_empty) begin  // Read only if enabled and not empty
        buf_out <= buf_mem[tail[ADDR_WIDTH-1:0]];   // Read data from memory
        tail <= tail + 1;                          // Increment binary read pointer
        tail_gray <= (tail + 1) ^ ((tail + 1) >> 1); // Convert binary to Gray code
    end
end

  ////////////////////////////////////////////////////////
 ///// Synchronize Read Pointer to Write Clock Domain ///
////////////////////////////////////////////////////////
always @(posedge wr_clk or posedge rst) begin
    if (rst) begin
        tail_gray_sync1 <= 0;   // Reset first stage synchronizer
        tail_gray_sync2 <= 0;   // Reset second stage synchronizer
    end 
    else begin
        tail_gray_sync1 <= tail_gray;       // First stage: Capture read pointer (Gray)
        tail_gray_sync2 <= tail_gray_sync1; // Second stage: Synchronize to write clock
    end
end

  ////////////////////////////////////////////////////////////
 ////// Synchronize Write Pointer to Read Clock Domain //////
////////////////////////////////////////////////////////////
always @(posedge rd_clk or posedge rst) begin
    if (rst) begin
        head_gray_sync1 <= 0;  // Reset first stage synchronizer
        head_gray_sync2 <= 0;  // Reset second stage synchronizer
    end 
    else begin
        head_gray_sync1 <= head_gray;       // First stage: Capture write pointer (Gray)
        head_gray_sync2 <= head_gray_sync1; // Second stage: Synchronize to read clock
    end
end

  ////////////////////////////////////////////////////////////
 /////// Update Empty Flag Based on Synchronized Pointers ///
////////////////////////////////////////////////////////////
always @(posedge rd_clk or posedge rst) begin
    if (rst) 
        buf_empty <= 1;           // FIFO is empty after reset
    else 
        buf_empty <= empty_flag;  // Update empty flag
end

  /////////////////////////////////////////////////////////
 ///// Update Full Flag Based on Synchronized Pointers ///
/////////////////////////////////////////////////////////
always @(posedge wr_clk or posedge rst) begin
    if (rst) 
        buf_full <= 0;           // FIFO is not full after reset
    else 
        buf_full <= full_flag;   // Update full flag
end

endmodule

async_fifo_TB.v
`timescale 1ns/1ps

module async_fifo_TB;

  // Parameters
  parameter DATA_WIDTH = 8;
  parameter DEPTH = 64;
  parameter ADDR_WIDTH = 6;  // Log2(64) = 6

  // Signals
  reg wclk, rclk, rst;                // Clocks and reset
  reg wr_en, rd_en;                   // Write and read enable
  reg [DATA_WIDTH-1:0] data_in;       // Data input
  wire [DATA_WIDTH-1:0] data_out;     // Data output
  wire buf_full, buf_empty;           // Status flags

  // FIFO DUT
  Asynch_Fifo uut (
    .wr_clk(wclk),
    .rd_clk(rclk),
    .rst(rst),
    .wr_en(wr_en),
    .rd_en(rd_en),
    .buf_in(data_in),
    .buf_out(data_out),
    .buf_full(buf_full),
    .buf_empty(buf_empty)
  );

  // Clock generation
  initial begin
    wclk = 0;
    forever #10 wclk = ~wclk;  // Write clock with 20ns period
  end

  initial begin
    rclk = 0;
    forever #35 rclk = ~rclk;  // Read clock with 70ns period
  end

  // Test Procedure
  integer i;
  reg [DATA_WIDTH-1:0] write_data_q[0:DEPTH-1];  // Queue to store written data for verification
  integer write_ptr = 0, read_ptr = 0;

  initial begin
    // Initialize signals
    rst = 1;
    wr_en = 0;
    rd_en = 0;
    data_in = 0;

    // Reset the FIFO
    #50 rst = 0;
    #50 rst = 1;

    // Test Write Operation
    $display("Starting Write Operation...");
    for (i = 0; i < DEPTH; i = i + 1) begin
      @(posedge wclk);
      if (!buf_full) begin
        wr_en = 1;
        data_in = $random % 256;  // Generate random 8-bit data
        write_data_q[write_ptr] = data_in;  // Store for verification
        write_ptr = write_ptr + 1;
        $display("Write: Data = %h, Time = %0t", data_in, $time);
      end else begin
        wr_en = 0;
        $display("FIFO Full at Time = %0t", $time);
      end
    end
    wr_en = 0;

    // Small delay before reading
    #100;

    // Test Read Operation
    $display("Starting Read Operation...");
    for (i = 0; i < DEPTH; i = i + 1) begin
      @(posedge rclk);
      if (!buf_empty) begin
        rd_en = 1;
        @(posedge rclk);  // Wait for data_out to settle
        if (data_out !== write_data_q[read_ptr]) begin
          $display("ERROR: Mismatch at Time = %0t: Expected = %h, Read = %h", 
                   $time, write_data_q[read_ptr], data_out);
        end else begin
          $display("Read: Data = %h, Time = %0t", data_out, $time);
        end
        read_ptr = read_ptr + 1;
      end else begin
        rd_en = 0;
        $display("FIFO Empty at Time = %0t", $time);
      end
    end
    rd_en = 0;

    // End of simulation
    #100;
    $display("Test Completed Successfully!");
    $finish;
  end

  // Dump waveforms for analysis
  initial begin
    $dumpfile("async_fifo_TB.vcd");
    $dumpvars(0, async_fifo_TB);
  end

endmodule

async_fifo_TB.vcd
$date
	Wed Dec 18 20:53:03 2024
$end
$version
	ModelSim Version 2020.1
$end
$timescale
	1ps
$end

$scope module async_fifo_TB $end
$var parameter 32 ! DATA_WIDTH $end
$var parameter 32 " DEPTH $end
$var parameter 32 # ADDR_WIDTH $end
$var reg 1 $ wclk $end
$var reg 1 % rclk $end
$var reg 1 & rst $end
$var reg 1 ' wr_en $end
$var reg 1 ( rd_en $end
$var reg 8 ) data_in [7:0] $end
$var wire 1 * data_out [7] $end
$var wire 1 + data_out [6] $end
$var wire 1 , data_out [5] $end
$var wire 1 - data_out [4] $end
$var wire 1 . data_out [3] $end
$var wire 1 / data_out [2] $end
$var wire 1 0 data_out [1] $end
$var wire 1 1 data_out [0] $end
$var wire 1 2 buf_full $end
$var wire 1 3 buf_empty $end
$var integer 32 4 i $end
$var integer 32 5 write_ptr $end
$var integer 32 6 read_ptr $end

$scope module uut $end
$var parameter 32 7 DEPTH $end
$var parameter 32 8 ADDR_WIDTH $end
$var wire 1 9 wr_clk $end
$var wire 1 : rd_clk $end
$var wire 1 ; rst $end
$var wire 1 < wr_en $end
$var wire 1 = rd_en $end
$var wire 1 > buf_in [7] $end
$var wire 1 ? buf_in [6] $end
$var wire 1 @ buf_in [5] $end
$var wire 1 A buf_in [4] $end
$var wire 1 B buf_in [3] $end
$var wire 1 C buf_in [2] $end
$var wire 1 D buf_in [1] $end
$var wire 1 E buf_in [0] $end
$var reg 8 F buf_out [7:0] $end
$var reg 1 G buf_empty $end
$var reg 1 H buf_full $end
$var reg 7 I head [6:0] $end
$var reg 7 J tail [6:0] $end
$var reg 7 K head_gray [6:0] $end
$var reg 7 L tail_gray [6:0] $end
$var reg 7 M head_gray_sync1 [6:0] $end
$var reg 7 N head_gray_sync2 [6:0] $end
$var reg 7 O tail_gray_sync1 [6:0] $end
$var reg 7 P tail_gray_sync2 [6:0] $end
$var wire 1 Q empty_flag $end
$var wire 1 R full_flag $end
$upscope $end
$upscope $end
$enddefinitions $end
#0
$dumpvars
0$
0%
1&
0'
0(
b0 )
bx F
1G
0H
b0 I
b0 J
b0 K
b0 L
b0 M
b0 N
b0 O
b0 P
b1000 !
b1000000 "
b110 #
b1000000 7
b110 8
bx 4
b0 5
b0 6
x1
x0
x/
x.
x-
x,
x+
x*
02
13
1Q
0R
0E
0D
0C
0B
0A
0@
0?
0>
0=
0<
1;
0:
09
$end
#10000
1$
19
#20000
0$
09
#30000
1$
19
#35000
1%
1:
#40000
0$
09
#50000
0&
1$
0;
19
#60000
0$
09
#70000
0%
1$
0:
19
#80000
0$
09
#90000
1$
19
#100000
1&
b0 4
0$
1;
09
#105000
1%
1:
#110000
1$
19
1'
b100100 )
b1 5
b1 4
1<
1C
1@
#120000
0$
09
#130000
1$
19
b10000001 )
b10 5
b10 4
1E
0C
0@
1>
#140000
0%
0$
0:
09
#150000
1$
19
b1001 )
b11 5
b11 4
1B
0>
#160000
0$
09
#170000
1$
19
b1100011 )
b100 5
b100 4
1D
0B
1@
1?
#175000
1%
1:
#180000
0$
09
#190000
1$
19
b1101 )
b101 5
b101 4
0D
1C
1B
0@
0?
#200000
0$
09
#210000
0%
1$
0:
19
b10001101 )
b110 5
b110 4
1>
#220000
0$
09
#230000
1$
19
b1100101 )
b111 5
b111 4
0B
1@
1?
0>
#240000
0$
09
#245000
1%
1:
#250000
1$
19
b10010 )
b1000 5
b1000 4
0E
1D
0C
1A
0@
0?
#260000
0$
09
#270000
1$
19
b1 )
b1001 5
b1001 4
1E
0D
0A
#280000
0%
0$
0:
09
#290000
1$
19
b1101 )
b1010 5
b1010 4
1C
1B
#300000
0$
09
#310000
1$
19
b1110110 )
b1011 5
b1011 4
0E
1D
0B
1A
1@
1?
#315000
1%
1:
#320000
0$
09
#330000
1$
19
b111101 )
b1100 5
b1100 4
1E
0D
1B
0?
#340000
0$
09
#350000
0%
1$
0:
19
b11101101 )
b1101 5
b1101 4
0A
1?
1>
#360000
0$
09
#370000
1$
19
b10001100 )
b1110 5
b1110 4
0E
0@
0?
#380000
0$
09
#385000
1%
1:
#390000
1$
19
b11111001 )
b1111 5
b1111 4
1E
0C
1A
1@
1?
#400000
0$
09
#410000
1$
19
b11000110 )
b10000 5
b10000 4
0E
1D
1C
0B
0A
0@
#420000
0%
0$
0:
09
#430000
1$
19
b11000101 )
b10001 5
b10001 4
1E
0D
#440000
0$
09
#450000
1$
19
b10101010 )
b10010 5
b10010 4
0E
1D
0C
1B
1@
0?
#455000
1%
1:
#460000
0$
09
#470000
1$
19
b11100101 )
b10011 5
b10011 4
1E
0D
1C
0B
1?
#480000
0$
09
#490000
0%
1$
0:
19
b1110111 )
b10100 5
b10100 4
1D
1A
0>
#500000
0$
09
#510000
1$
19
b10010 )
b10101 5
b10101 4
0E
0C
0@
0?
#520000
0$
09
#525000
1%
1:
#530000
1$
19
b10001111 )
b10110 5
b10110 4
1E
1C
1B
0A
1>
#540000
0$
09
#550000
1$
19
b11110010 )
b10111 5
b10111 4
0E
0C
0B
1A
1@
1?
#560000
0%
0$
0:
09
#570000
1$
19
b11001110 )
b11000 5
b11000 4
1C
1B
0A
0@
#580000
0$
09
#590000
1$
19
b11101000 )
b11001 5
b11001 4
0D
0C
1@
#595000
1%
1:
#600000
0$
09
#610000
1$
19
b11000101 )
b11010 5
b11010 4
1E
1C
0B
0@
#620000
0$
09
#630000
0%
1$
0:
19
b1011100 )
b11011 5
b11011 4
0E
1B
1A
0>
#640000
0$
09
#650000
1$
19
b10111101 )
b11100 5
b11100 4
1E
1@
0?
1>
#660000
0$
09
#665000
1%
1:
#670000
1$
19
b101101 )
b11101 5
b11101 4
0A
0>
#680000
0$
09
#690000
1$
19
b1100101 )
b11110 5
b11110 4
0B
1?
#700000
0%
0$
0:
09
#710000
1$
19
b1100011 )
b11111 5
b11111 4
1D
0C
#720000
0$
09
#730000
1$
19
b1010 )
b100000 5
b100000 4
0E
1B
0@
0?
#735000
1%
1:
#740000
0$
09
#750000
1$
19
b10000000 )
b100001 5
b100001 4
0D
0B
1>
#760000
0$
09
#770000
0%
1$
0:
19
b100000 )
b100010 5
b100010 4
1@
0>
#780000
0$
09
#790000
1$
19
b10101010 )
b100011 5
b100011 4
1D
1B
1>
#800000
0$
09
#805000
1%
1:
#810000
1$
19
b10011101 )
b100100 5
b100100 4
1E
0D
1C
1A
0@
#820000
0$
09
#830000
1$
19
b10010110 )
b100101 5
b100101 4
0E
1D
0B
#840000
0%
0$
0:
09
#850000
1$
19
b10011 )
b100110 5
b100110 4
1E
0C
0>
#860000
0$
09
#870000
1$
19
b1101 )
b100111 5
b100111 4
0D
1C
1B
0A
#875000
1%
1:
#880000
0$
09
#890000
1$
19
b1010011 )
b101000 5
b101000 4
1D
0C
0B
1A
1?
#900000
0$
09
#910000
0%
1$
0:
19
b1101011 )
b101001 5
b101001 4
1B
0A
1@
#920000
0$
09
#930000
1$
19
b11010101 )
b101010 5
b101010 4
0D
1C
0B
1A
0@
1>
#940000
0$
09
#945000
1%
1:
#950000
1$
19
b10 )
b101011 5
b101011 4
0E
1D
0C
0A
0?
0>
#960000
0$
09
#970000
1$
19
b10101110 )
b101100 5
b101100 4
1C
1B
1@
1>
#980000
0%
0$
0:
09
#990000
1$
19
b11101 )
b101101 5
b101101 4
1E
0D
1A
0@
0>
#1000000
0$
09
#1010000
1$
19
b11001111 )
b101110 5
b101110 4
1D
0A
1?
1>
#1015000
1%
1:
#1020000
0$
09
#1030000
1$
19
b100011 )
b101111 5
b101111 4
0C
0B
1@
0?
0>
#1040000
0$
09
#1050000
0%
1$
0:
19
b1010 )
b110000 5
b110000 4
0E
1B
0@
#1060000
0$
09
#1070000
1$
19
b11001010 )
b110001 5
b110001 4
1?
1>
#1080000
0$
09
#1085000
1%
1:
#1090000
1$
19
b111100 )
b110010 5
b110010 4
0D
1C
1A
1@
0?
0>
#1100000
0$
09
#1110000
1$
19
b11110010 )
b110011 5
b110011 4
1D
0C
0B
1?
1>
#1120000
0%
0$
0:
09
#1130000
1$
19
b10001010 )
b110100 5
b110100 4
1B
0A
0@
0?
#1140000
0$
09
#1150000
1$
19
b1000001 )
b110101 5
b110101 4
1E
0D
0B
1?
0>
#1155000
1%
1:
#1160000
0$
09
#1170000
1$
19
b11011000 )
b110110 5
b110110 4
0E
1B
1A
1>
#1180000
0$
09
#1190000
0%
1$
0:
19
b1111000 )
b110111 5
b110111 4
1@
0>
#1200000
0$
09
#1210000
1$
19
b10001001 )
b111000 5
b111000 4
1E
0A
0@
0?
1>
#1220000
0$
09
#1225000
1%
1:
#1230000
1$
19
b11101011 )
b111001 5
b111001 4
1D
1@
1?
#1240000
0$
09
#1250000
1$
19
b10110110 )
b111010 5
b111010 4
0E
1C
0B
1A
0?
#1260000
0%
0$
0:
09
#1270000
1$
19
b11000110 )
b111011 5
b111011 4
0A
0@
1?
#1280000
0$
09
#1290000
1$
19
b10101110 )
b111100 5
b111100 4
1B
1@
0?
#1295000
1%
1:
#1300000
0$
09
#1310000
1$
19
b10111100 )
b111101 5
b111101 4
0D
1A
#1320000
0$
09
#1330000
0%
1$
0:
19
b101010 )
b111110 5
b111110 4
1D
0C
0A
0>
#1340000
0$
09
#1350000
1$
19
b1011 )
b111111 5
b111111 4
1E
0@
#1360000
0$
09
#1365000
1%
1:
#1370000
1$
19
b1110001 )
b1000000 5
b1000000 4
0'
0D
0B
1A
1@
1?
0<
#1380000
0$
09
#1390000
1$
19
#1400000
0%
0$
0:
09
#1410000
1$
19
#1420000
0$
09
#1430000
1$
19
#1435000
1%
1:
#1440000
0$
09
#1450000
1$
19
#1460000
0$
09
#1470000
b0 4
0%
1$
0:
19
#1480000
0$
09
#1490000
1$
19
#1500000
0$
09
#1505000
1%
1:
b1 4
#1510000
1$
19
#1520000
0$
09
#1530000
1$
19
#1540000
0%
0$
0:
09
#1550000
1$
19
#1560000
0$
09
#1570000
1$
19
#1575000
1%
1:
b10 4
#1580000
0$
09
#1590000
1$
19
#1600000
0$
09
#1610000
0%
1$
0:
19
#1620000
0$
09
#1630000
1$
19
#1640000
0$
09
#1645000
1%
1:
b11 4
#1650000
1$
19
#1660000
0$
09
#1670000
1$
19
#1680000
0%
0$
0:
09
#1690000
1$
19
#1700000
0$
09
#1710000
1$
19
#1715000
1%
1:
b100 4
#1720000
0$
09
#1730000
1$
19
#1740000
0$
09
#1750000
0%
1$
0:
19
#1760000
0$
09
#1770000
1$
19
#1780000
0$
09
#1785000
1%
1:
b101 4
#1790000
1$
19
#1800000
0$
09
#1810000
1$
19
#1820000
0%
0$
0:
09
#1830000
1$
19
#1840000
0$
09
#1850000
1$
19
#1855000
1%
1:
b110 4
#1860000
0$
09
#1870000
1$
19
#1880000
0$
09
#1890000
0%
1$
0:
19
#1900000
0$
09
#1910000
1$
19
#1920000
0$
09
#1925000
1%
1:
b111 4
#1930000
1$
19
#1940000
0$
09
#1950000
1$
19
#1960000
0%
0$
0:
09
#1970000
1$
19
#1980000
0$
09
#1990000
1$
19
#1995000
1%
1:
b1000 4
#2000000
0$
09
#2010000
1$
19
#2020000
0$
09
#2030000
0%
1$
0:
19
#2040000
0$
09
#2050000
1$
19
#2060000
0$
09
#2065000
1%
1:
b1001 4
#2070000
1$
19
#2080000
0$
09
#2090000
1$
19
#2100000
0%
0$
0:
09
#2110000
1$
19
#2120000
0$
09
#2130000
1$
19
#2135000
1%
1:
b1010 4
#2140000
0$
09
#2150000
1$
19
#2160000
0$
09
#2170000
0%
1$
0:
19
#2180000
0$
09
#2190000
1$
19
#2200000
0$
09
#2205000
1%
1:
b1011 4
#2210000
1$
19
#2220000
0$
09
#2230000
1$
19
#2240000
0%
0$
0:
09
#2250000
1$
19
#2260000
0$
09
#2270000
1$
19
#2275000
1%
1:
b1100 4
#2280000
0$
09
#2290000
1$
19
#2300000
0$
09
#2310000
0%
1$
0:
19
#2320000
0$
09
#2330000
1$
19
#2340000
0$
09
#2345000
1%
1:
b1101 4
#2350000
1$
19
#2360000
0$
09
#2370000
1$
19
#2380000
0%
0$
0:
09
#2390000
1$
19
#2400000
0$
09
#2410000
1$
19
#2415000
1%
1:
b1110 4
#2420000
0$
09
#2430000
1$
19
#2440000
0$
09
#2450000
0%
1$
0:
19
#2460000
0$
09
#2470000
1$
19
#2480000
0$
09
#2485000
1%
1:
b1111 4
#2490000
1$
19
#2500000
0$
09
#2510000
1$
19
#2520000
0%
0$
0:
09
#2530000
1$
19
#2540000
0$
09
#2550000
1$
19
#2555000
1%
1:
b10000 4
#2560000
0$
09
#2570000
1$
19
#2580000
0$
09
#2590000
0%
1$
0:
19
#2600000
0$
09
#2610000
1$
19
#2620000
0$
09
#2625000
1%
1:
b10001 4
#2630000
1$
19
#2640000
0$
09
#2650000
1$
19
#2660000
0%
0$
0:
09
#2670000
1$
19
#2680000
0$
09
#2690000
1$
19
#2695000
1%
1:
b10010 4
#2700000
0$
09
#2710000
1$
19
#2720000
0$
09
#2730000
0%
1$
0:
19
#2740000
0$
09
#2750000
1$
19
#2760000
0$
09
#2765000
1%
1:
b10011 4
#2770000
1$
19
#2780000
0$
09
#2790000
1$
19
#2800000
0%
0$
0:
09
#2810000
1$
19
#2820000
0$
09
#2830000
1$
19
#2835000
1%
1:
b10100 4
#2840000
0$
09
#2850000
1$
19
#2860000
0$
09
#2870000
0%
1$
0:
19
#2880000
0$
09
#2890000
1$
19
#2900000
0$
09
#2905000
1%
1:
b10101 4
#2910000
1$
19
#2920000
0$
09
#2930000
1$
19
#2940000
0%
0$
0:
09
#2950000
1$
19
#2960000
0$
09
#2970000
1$
19
#2975000
1%
1:
b10110 4
#2980000
0$
09
#2990000
1$
19
#3000000
0$
09
#3010000
0%
1$
0:
19
#3020000
0$
09
#3030000
1$
19
#3040000
0$
09
#3045000
1%
1:
b10111 4
#3050000
1$
19
#3060000
0$
09
#3070000
1$
19
#3080000
0%
0$
0:
09
#3090000
1$
19
#3100000
0$
09
#3110000
1$
19
#3115000
1%
1:
b11000 4
#3120000
0$
09
#3130000
1$
19
#3140000
0$
09
#3150000
0%
1$
0:
19
#3160000
0$
09
#3170000
1$
19
#3180000
0$
09
#3185000
1%
1:
b11001 4
#3190000
1$
19
#3200000
0$
09
#3210000
1$
19
#3220000
0%
0$
0:
09
#3230000
1$
19
#3240000
0$
09
#3250000
1$
19
#3255000
1%
1:
b11010 4
#3260000
0$
09
#3270000
1$
19
#3280000
0$
09
#3290000
0%
1$
0:
19
#3300000
0$
09
#3310000
1$
19
#3320000
0$
09
#3325000
1%
1:
b11011 4
#3330000
1$
19
#3340000
0$
09
#3350000
1$
19
#3360000
0%
0$
0:
09
#3370000
1$
19
#3380000
0$
09
#3390000
1$
19
#3395000
1%
1:
b11100 4
#3400000
0$
09
#3410000
1$
19
#3420000
0$
09
#3430000
0%
1$
0:
19
#3440000
0$
09
#3450000
1$
19
#3460000
0$
09
#3465000
1%
1:
b11101 4
#3470000
1$
19
#3480000
0$
09
#3490000
1$
19
#3500000
0%
0$
0:
09
#3510000
1$
19
#3520000
0$
09
#3530000
1$
19
#3535000
1%
1:
b11110 4
#3540000
0$
09
#3550000
1$
19
#3560000
0$
09
#3570000
0%
1$
0:
19
#3580000
0$
09
#3590000
1$
19
#3600000
0$
09
#3605000
1%
1:
b11111 4
#3610000
1$
19
#3620000
0$
09
#3630000
1$
19
#3640000
0%
0$
0:
09
#3650000
1$
19
#3660000
0$
09
#3670000
1$
19
#3675000
1%
1:
b100000 4
#3680000
0$
09
#3690000
1$
19
#3700000
0$
09
#3710000
0%
1$
0:
19
#3720000
0$
09
#3730000
1$
19
#3740000
0$
09
#3745000
1%
1:
b100001 4
#3750000
1$
19
#3760000
0$
09
#3770000
1$
19
#3780000
0%
0$
0:
09
#3790000
1$
19
#3800000
0$
09
#3810000
1$
19
#3815000
1%
1:
b100010 4
#3820000
0$
09
#3830000
1$
19
#3840000
0$
09
#3850000
0%
1$
0:
19
#3860000
0$
09
#3870000
1$
19
#3880000
0$
09
#3885000
1%
1:
b100011 4
#3890000
1$
19
#3900000
0$
09
#3910000
1$
19
#3920000
0%
0$
0:
09
#3930000
1$
19
#3940000
0$
09
#3950000
1$
19
#3955000
1%
1:
b100100 4
#3960000
0$
09
#3970000
1$
19
#3980000
0$
09
#3990000
0%
1$
0:
19
#4000000
0$
09
#4010000
1$
19
#4020000
0$
09
#4025000
1%
1:
b100101 4
#4030000
1$
19
#4040000
0$
09
#4050000
1$
19
#4060000
0%
0$
0:
09
#4070000
1$
19
#4080000
0$
09
#4090000
1$
19
#4095000
1%
1:
b100110 4
#4100000
0$
09
#4110000
1$
19
#4120000
0$
09
#4130000
0%
1$
0:
19
#4140000
0$
09
#4150000
1$
19
#4160000
0$
09
#4165000
1%
1:
b100111 4
#4170000
1$
19
#4180000
0$
09
#4190000
1$
19
#4200000
0%
0$
0:
09
#4210000
1$
19
#4220000
0$
09
#4230000
1$
19
#4235000
1%
1:
b101000 4
#4240000
0$
09
#4250000
1$
19
#4260000
0$
09
#4270000
0%
1$
0:
19
#4280000
0$
09
#4290000
1$
19
#4300000
0$
09
#4305000
1%
1:
b101001 4
#4310000
1$
19
#4320000
0$
09
#4330000
1$
19
#4340000
0%
0$
0:
09
#4350000
1$
19
#4360000
0$
09
#4370000
1$
19
#4375000
1%
1:
b101010 4
#4380000
0$
09
#4390000
1$
19
#4400000
0$
09
#4410000
0%
1$
0:
19
#4420000
0$
09
#4430000
1$
19
#4440000
0$
09
#4445000
1%
1:
b101011 4
#4450000
1$
19
#4460000
0$
09
#4470000
1$
19
#4480000
0%
0$
0:
09
#4490000
1$
19
#4500000
0$
09
#4510000
1$
19
#4515000
1%
1:
b101100 4
#4520000
0$
09
#4530000
1$
19
#4540000
0$
09
#4550000
0%
1$
0:
19
#4560000
0$
09
#4570000
1$
19
#4580000
0$
09
#4585000
1%
1:
b101101 4
#4590000
1$
19
#4600000
0$
09
#4610000
1$
19
#4620000
0%
0$
0:
09
#4630000
1$
19
#4640000
0$
09
#4650000
1$
19
#4655000
1%
1:
b101110 4
#4660000
0$
09
#4670000
1$
19
#4680000
0$
09
#4690000
0%
1$
0:
19
#4700000
0$
09
#4710000
1$
19
#4720000
0$
09
#4725000
1%
1:
b101111 4
#4730000
1$
19
#4740000
0$
09
#4750000
1$
19
#4760000
0%
0$
0:
09
#4770000
1$
19
#4780000
0$
09
#4790000
1$
19
#4795000
1%
1:
b110000 4
#4800000
0$
09
#4810000
1$
19
#4820000
0$
09
#4830000
0%
1$
0:
19
#4840000
0$
09
#4850000
1$
19
#4860000
0$
09
#4865000
1%
1:
b110001 4
#4870000
1$
19
#4880000
0$
09
#4890000
1$
19
#4900000
0%
0$
0:
09
#4910000
1$
19
#4920000
0$
09
#4930000
1$
19
#4935000
1%
1:
b110010 4
#4940000
0$
09
#4950000
1$
19
#4960000
0$
09
#4970000
0%
1$
0:
19
#4980000
0$
09
#4990000
1$
19
#5000000
0$
09
#5005000
1%
1:
b110011 4
#5010000
1$
19
#5020000
0$
09
#5030000
1$
19
#5040000
0%
0$
0:
09
#5050000
1$
19
#5060000
0$
09
#5070000
1$
19
#5075000
1%
1:
b110100 4
#5080000
0$
09
#5090000
1$
19
#5100000
0$
09
#5110000
0%
1$
0:
19
#5120000
0$
09
#5130000
1$
19
#5140000
0$
09
#5145000
1%
1:
b110101 4
#5150000
1$
19
#5160000
0$
09
#5170000
1$
19
#5180000
0%
0$
0:
09
#5190000
1$
19
#5200000
0$
09
#5210000
1$
19
#5215000
1%
1:
b110110 4
#5220000
0$
09
#5230000
1$
19
#5240000
0$
09
#5250000
0%
1$
0:
19
#5260000
0$
09
#5270000
1$
19
#5280000
0$
09
#5285000
1%
1:
b110111 4
#5290000
1$
19
#5300000
0$
09
#5310000
1$
19
#5320000
0%
0$
0:
09
#5330000
1$
19
#5340000
0$
09
#5350000
1$
19
#5355000
1%
1:
b111000 4
#5360000
0$
09
#5370000
1$
19
#5380000
0$
09
#5390000
0%
1$
0:
19
#5400000
0$
09
#5410000
1$
19
#5420000
0$
09
#5425000
1%
1:
b111001 4
#5430000
1$
19
#5440000
0$
09
#5450000
1$
19
#5460000
0%
0$
0:
09
#5470000
1$
19
#5480000
0$
09
#5490000
1$
19
#5495000
1%
1:
b111010 4
#5500000
0$
09
#5510000
1$
19
#5520000
0$
09
#5530000
0%
1$
0:
19
#5540000
0$
09
#5550000
1$
19
#5560000
0$
09
#5565000
1%
1:
b111011 4
#5570000
1$
19
#5580000
0$
09
#5590000
1$
19
#5600000
0%
0$
0:
09
#5610000
1$
19
#5620000
0$
09
#5630000
1$
19
#5635000
1%
1:
b111100 4
#5640000
0$
09
#5650000
1$
19
#5660000
0$
09
#5670000
0%
1$
0:
19
#5680000
0$
09
#5690000
1$
19
#5700000
0$
09
#5705000
1%
1:
b111101 4
#5710000
1$
19
#5720000
0$
09
#5730000
1$
19
#5740000
0%
0$
0:
09
#5750000
1$
19
#5760000
0$
09
#5770000
1$
19
#5775000
1%
1:
b111110 4
#5780000
0$
09
#5790000
1$
19
#5800000
0$
09
#5810000
0%
1$
0:
19
#5820000
0$
09
#5830000
1$
19
#5840000
0$
09
#5845000
1%
1:
b111111 4
#5850000
1$
19
#5860000
0$
09
#5870000
1$
19
#5880000
0%
0$
0:
09
#5890000
1$
19
#5900000
0$
09
#5910000
1$
19
#5915000
1%
1:
b1000000 4
